myapimovies/__init__.py
myapimovies/myapimovies.py
myapimovies-0.0.3.dist-info/LICENSE
myapimovies-0.0.3.dist-info/METADATA
myapimovies-0.0.3.dist-info/WHEEL
myapimovies-0.0.3.dist-info/top_level.txt
myapimovies-0.0.3.dist-info/RECORD
