Metadata-Version: 2.1
Name: myapimovies
Version: 0.0.3
Summary: API client for MyApiMovies
Author-email: Alberto Rosa <admin@myapimovies.com>
Project-URL: Homepage, https://www.myapimovies.com/
Classifier: Development Status :: 4 - Beta
Classifier: Programming Language :: Python :: 3
Classifier: Operating System :: OS Independent
Classifier: License :: OSI Approved :: GNU General Public License v3 (GPLv3)
Requires-Python: >=3.0
License-File: LICENSE
Requires-Dist: requests (>=2.21.0)
